<invoice><tipo>fatura_telecom</tipo><operadora><nome>Vivo</nome><cnpj>00.000.000/0001-01</cnpj></operadora><cliente><razaoSocial>Empresa Delta Telecom</razaoSocial><cnpj>10000860/0001-60</cnpj></cliente><contrato><numero>47305347</numero></contrato><periodoReferencia><inicio>2025-12-01T23:22:08.116856Z</inicio><fim>2025-12-31T23:22:08.116856Z</fim></periodoReferencia><datas><emissao>2026-01-01T23:22:08.116856Z</emissao><vencimento>2026-02-01T00:00:00Z</vencimento></datas><moeda>BRL</moeda><itens><item><categoria>voz</categoria><descricao>Voz Ilimitada</descricao><quantidade>1</quantidade><unidade>linha</unidade><valorBase>157.07</valorBase><impostos><item><tipo>ICMS</tipo><aliquota>0.25</aliquota><baseCalculo>157.07</baseCalculo><valor>39.27</valor></item><item><tipo>PIS</tipo><aliquota>0.0165</aliquota><baseCalculo>157.07</baseCalculo><valor>2.59</valor></item><item><tipo>COFINS</tipo><aliquota>0.076</aliquota><baseCalculo>157.07</baseCalculo><valor>11.94</valor></item></impostos><subtotalImpostos>53.8</subtotalImpostos><total>210.87</total></item><item><categoria>televisao</categoria><descricao>TV HD Empresarial (1 ponto)</descricao><quantidade>1</quantidade><unidade>ponto</unidade><valorBase>191.57</valorBase><impostos><item><tipo>ICMS</tipo><aliquota>0.25</aliquota><baseCalculo>191.57</baseCalculo><valor>47.89</valor></item><item><tipo>PIS</tipo><aliquota>0.0165</aliquota><baseCalculo>191.57</baseCalculo><valor>3.16</valor></item><item><tipo>COFINS</tipo><aliquota>0.076</aliquota><baseCalculo>191.57</baseCalculo><valor>14.56</valor></item></impostos><subtotalImpostos>65.61</subtotalImpostos><total>257.18</total></item><item><categoria>iot</categoria><descricao>Conectividade IoT</descricao><quantidade>1</quantidade><unidade>servico</unidade><valorBase>40.7</valorBase><impostos><item><tipo>ICMS</tipo><aliquota>0.25</aliquota><baseCalculo>40.7</baseCalculo><valor>10.18</valor></item><item><tipo>PIS</tipo><aliquota>0.0165</aliquota><baseCalculo>40.7</baseCalculo><valor>0.67</valor></item><item><tipo>COFINS</tipo><aliquota>0.076</aliquota><baseCalculo>40.7</baseCalculo><valor>3.09</valor></item></impostos><subtotalImpostos>13.94</subtotalImpostos><total>54.64</total></item></itens><totais><valorServicosSemImpostos>389.34</valorServicosSemImpostos><impostos><ICMS>97.34</ICMS><PIS>6.42</PIS><COFINS>29.59</COFINS></impostos><totalImpostos>133.35</totalImpostos><totalGeral>522.69</totalGeral></totais><pagamento><metodo>debito_automatico</metodo><status>em_aberto</status></pagamento><auditoria><criadoEm>2026-01-01T23:22:08.116856Z</criadoEm><atualizadoEm>2026-01-01T23:22:08.116856Z</atualizadoEm><fonte>mock_generator</fonte></auditoria></invoice>