<invoice><tipo>fatura_telecom</tipo><operadora><nome>Vivo</nome><cnpj>00.000.000/0001-01</cnpj></operadora><cliente><razaoSocial>Empresa Sigma Networks</razaoSocial><cnpj>10000895/0001-95</cnpj></cliente><contrato><numero>48383585</numero></contrato><periodoReferencia><inicio>2025-10-01T23:22:08.123932Z</inicio><fim>2025-10-31T23:22:08.123932Z</fim></periodoReferencia><datas><emissao>2025-11-01T23:22:08.123932Z</emissao><vencimento>2026-02-01T00:00:00Z</vencimento></datas><moeda>BRL</moeda><itens><item><categoria>voz</categoria><descricao>Voz Ilimitada</descricao><quantidade>1</quantidade><unidade>linha</unidade><valorBase>173.74</valorBase><impostos><item><tipo>ICMS</tipo><aliquota>0.25</aliquota><baseCalculo>173.74</baseCalculo><valor>43.44</valor></item><item><tipo>PIS</tipo><aliquota>0.0165</aliquota><baseCalculo>173.74</baseCalculo><valor>2.87</valor></item><item><tipo>COFINS</tipo><aliquota>0.076</aliquota><baseCalculo>173.74</baseCalculo><valor>13.2</valor></item></impostos><subtotalImpostos>59.51</subtotalImpostos><total>233.25</total></item><item><categoria>voz</categoria><descricao>Voz Ilimitada</descricao><quantidade>1</quantidade><unidade>linha</unidade><valorBase>164.65</valorBase><impostos><item><tipo>ICMS</tipo><aliquota>0.25</aliquota><baseCalculo>164.65</baseCalculo><valor>41.16</valor></item><item><tipo>PIS</tipo><aliquota>0.0165</aliquota><baseCalculo>164.65</baseCalculo><valor>2.72</valor></item><item><tipo>COFINS</tipo><aliquota>0.076</aliquota><baseCalculo>164.65</baseCalculo><valor>12.51</valor></item></impostos><subtotalImpostos>56.39</subtotalImpostos><total>221.04</total></item></itens><totais><valorServicosSemImpostos>338.39</valorServicosSemImpostos><impostos><ICMS>84.6</ICMS><PIS>5.59</PIS><COFINS>25.71</COFINS></impostos><totalImpostos>115.9</totalImpostos><totalGeral>454.29</totalGeral></totais><pagamento><metodo>debito_automatico</metodo><status>em_aberto</status></pagamento><auditoria><criadoEm>2025-11-01T23:22:08.123932Z</criadoEm><atualizadoEm>2025-11-01T23:22:08.123932Z</atualizadoEm><fonte>mock_generator</fonte></auditoria></invoice>