<invoice><tipo>fatura_telecom</tipo><operadora><nome>Vivo</nome><cnpj>00.000.000/0001-01</cnpj></operadora><cliente><razaoSocial>Empresa Gamma Tech</razaoSocial><cnpj>10000590/0001-60</cnpj></cliente><contrato><numero>46287327</numero></contrato><periodoReferencia><inicio>2026-01-01T23:22:08.066321Z</inicio><fim>2026-01-31T23:22:08.066321Z</fim></periodoReferencia><datas><emissao>2026-02-01T23:22:08.066321Z</emissao><vencimento>2026-02-01T00:00:00Z</vencimento></datas><moeda>BRL</moeda><itens><item><categoria>iot</categoria><descricao>Conectividade IoT</descricao><quantidade>1</quantidade><unidade>servico</unidade><valorBase>163.71</valorBase><impostos><item><tipo>ICMS</tipo><aliquota>0.25</aliquota><baseCalculo>163.71</baseCalculo><valor>40.93</valor></item><item><tipo>PIS</tipo><aliquota>0.0165</aliquota><baseCalculo>163.71</baseCalculo><valor>2.7</valor></item><item><tipo>COFINS</tipo><aliquota>0.076</aliquota><baseCalculo>163.71</baseCalculo><valor>12.44</valor></item></impostos><subtotalImpostos>56.07</subtotalImpostos><total>219.78</total></item><item><categoria>iot</categoria><descricao>Conectividade IoT</descricao><quantidade>1</quantidade><unidade>servico</unidade><valorBase>69.45</valorBase><impostos><item><tipo>ICMS</tipo><aliquota>0.25</aliquota><baseCalculo>69.45</baseCalculo><valor>17.36</valor></item><item><tipo>PIS</tipo><aliquota>0.0165</aliquota><baseCalculo>69.45</baseCalculo><valor>1.15</valor></item><item><tipo>COFINS</tipo><aliquota>0.076</aliquota><baseCalculo>69.45</baseCalculo><valor>5.28</valor></item></impostos><subtotalImpostos>23.79</subtotalImpostos><total>93.24</total></item><item><categoria>voz</categoria><descricao>Voz Ilimitada</descricao><quantidade>1</quantidade><unidade>linha</unidade><valorBase>59.23</valorBase><impostos><item><tipo>ICMS</tipo><aliquota>0.25</aliquota><baseCalculo>59.23</baseCalculo><valor>14.81</valor></item><item><tipo>PIS</tipo><aliquota>0.0165</aliquota><baseCalculo>59.23</baseCalculo><valor>0.98</valor></item><item><tipo>COFINS</tipo><aliquota>0.076</aliquota><baseCalculo>59.23</baseCalculo><valor>4.5</valor></item></impostos><subtotalImpostos>20.29</subtotalImpostos><total>79.52</total></item><item><categoria>celular</categoria><descricao>Plano Pós-Pago 20GB</descricao><quantidade>1</quantidade><unidade>linha</unidade><valorBase>98.84</valorBase><impostos><item><tipo>ICMS</tipo><aliquota>0.25</aliquota><baseCalculo>98.84</baseCalculo><valor>24.71</valor></item><item><tipo>PIS</tipo><aliquota>0.0165</aliquota><baseCalculo>98.84</baseCalculo><valor>1.63</valor></item><item><tipo>COFINS</tipo><aliquota>0.076</aliquota><baseCalculo>98.84</baseCalculo><valor>7.51</valor></item></impostos><subtotalImpostos>33.85</subtotalImpostos><total>132.69</total></item><item><categoria>celular</categoria><descricao>Plano Pós-Pago 20GB</descricao><quantidade>1</quantidade><unidade>linha</unidade><valorBase>125.45</valorBase><impostos><item><tipo>ICMS</tipo><aliquota>0.25</aliquota><baseCalculo>125.45</baseCalculo><valor>31.36</valor></item><item><tipo>PIS</tipo><aliquota>0.0165</aliquota><baseCalculo>125.45</baseCalculo><valor>2.07</valor></item><item><tipo>COFINS</tipo><aliquota>0.076</aliquota><baseCalculo>125.45</baseCalculo><valor>9.53</valor></item></impostos><subtotalImpostos>42.96</subtotalImpostos><total>168.41</total></item></itens><totais><valorServicosSemImpostos>516.68</valorServicosSemImpostos><impostos><ICMS>129.17</ICMS><PIS>8.53</PIS><COFINS>39.26</COFINS></impostos><totalImpostos>176.96</totalImpostos><totalGeral>693.64</totalGeral></totais><pagamento><metodo>debito_automatico</metodo><status>em_aberto</status></pagamento><auditoria><criadoEm>2026-02-01T23:22:08.066321Z</criadoEm><atualizadoEm>2026-02-01T23:22:08.066321Z</atualizadoEm><fonte>mock_generator</fonte></auditoria></invoice>