<invoice><tipo>fatura_telecom</tipo><operadora><nome>Vivo</nome><cnpj>00.000.000/0001-01</cnpj></operadora><cliente><razaoSocial>Empresa Sigma Networks</razaoSocial><cnpj>10000251/0001-81</cnpj></cliente><contrato><numero>45770581</numero></contrato><periodoReferencia><inicio>2025-11-01T23:22:07.994344Z</inicio><fim>2025-12-01T23:22:07.994344Z</fim></periodoReferencia><datas><emissao>2025-12-02T23:22:07.994344Z</emissao><vencimento>2026-02-01T00:00:00Z</vencimento></datas><moeda>BRL</moeda><itens><item><categoria>fibra</categoria><descricao>Internet Fibra 300 Mbps</descricao><quantidade>1</quantidade><unidade>servico</unidade><valorBase>159.02</valorBase><impostos><item><tipo>ICMS</tipo><aliquota>0.25</aliquota><baseCalculo>159.02</baseCalculo><valor>39.76</valor></item><item><tipo>PIS</tipo><aliquota>0.0165</aliquota><baseCalculo>159.02</baseCalculo><valor>2.62</valor></item><item><tipo>COFINS</tipo><aliquota>0.076</aliquota><baseCalculo>159.02</baseCalculo><valor>12.09</valor></item></impostos><subtotalImpostos>54.47</subtotalImpostos><total>213.49</total></item><item><categoria>televisao</categoria><descricao>TV HD Empresarial (1 ponto)</descricao><quantidade>1</quantidade><unidade>ponto</unidade><valorBase>94.92</valorBase><impostos><item><tipo>ICMS</tipo><aliquota>0.25</aliquota><baseCalculo>94.92</baseCalculo><valor>23.73</valor></item><item><tipo>PIS</tipo><aliquota>0.0165</aliquota><baseCalculo>94.92</baseCalculo><valor>1.57</valor></item><item><tipo>COFINS</tipo><aliquota>0.076</aliquota><baseCalculo>94.92</baseCalculo><valor>7.21</valor></item></impostos><subtotalImpostos>32.51</subtotalImpostos><total>127.43</total></item><item><categoria>televisao</categoria><descricao>TV HD Empresarial (1 ponto)</descricao><quantidade>1</quantidade><unidade>ponto</unidade><valorBase>180.35</valorBase><impostos><item><tipo>ICMS</tipo><aliquota>0.25</aliquota><baseCalculo>180.35</baseCalculo><valor>45.09</valor></item><item><tipo>PIS</tipo><aliquota>0.0165</aliquota><baseCalculo>180.35</baseCalculo><valor>2.98</valor></item><item><tipo>COFINS</tipo><aliquota>0.076</aliquota><baseCalculo>180.35</baseCalculo><valor>13.71</valor></item></impostos><subtotalImpostos>61.78</subtotalImpostos><total>242.13</total></item></itens><totais><valorServicosSemImpostos>434.29</valorServicosSemImpostos><impostos><ICMS>108.58</ICMS><PIS>7.17</PIS><COFINS>33.01</COFINS></impostos><totalImpostos>148.76</totalImpostos><totalGeral>583.05</totalGeral></totais><pagamento><metodo>debito_automatico</metodo><status>em_aberto</status></pagamento><auditoria><criadoEm>2025-12-02T23:22:07.994344Z</criadoEm><atualizadoEm>2025-12-02T23:22:07.994344Z</atualizadoEm><fonte>mock_generator</fonte></auditoria></invoice>