<invoice><tipo>fatura_telecom</tipo><operadora><nome>Vivo</nome><cnpj>00.000.000/0001-01</cnpj></operadora><cliente><razaoSocial>Empresa Gamma Tech</razaoSocial><cnpj>10000128/0001-48</cnpj></cliente><contrato><numero>48111685</numero></contrato><periodoReferencia><inicio>2025-12-01T23:22:07.966074Z</inicio><fim>2025-12-31T23:22:07.966074Z</fim></periodoReferencia><datas><emissao>2026-01-01T23:22:07.966074Z</emissao><vencimento>2026-02-01T00:00:00Z</vencimento></datas><moeda>BRL</moeda><itens><item><categoria>voz</categoria><descricao>Voz Ilimitada</descricao><quantidade>1</quantidade><unidade>linha</unidade><valorBase>133.28</valorBase><impostos><item><tipo>ICMS</tipo><aliquota>0.25</aliquota><baseCalculo>133.28</baseCalculo><valor>33.32</valor></item><item><tipo>PIS</tipo><aliquota>0.0165</aliquota><baseCalculo>133.28</baseCalculo><valor>2.2</valor></item><item><tipo>COFINS</tipo><aliquota>0.076</aliquota><baseCalculo>133.28</baseCalculo><valor>10.13</valor></item></impostos><subtotalImpostos>45.65</subtotalImpostos><total>178.93</total></item><item><categoria>iot</categoria><descricao>Conectividade IoT</descricao><quantidade>1</quantidade><unidade>servico</unidade><valorBase>199.4</valorBase><impostos><item><tipo>ICMS</tipo><aliquota>0.25</aliquota><baseCalculo>199.4</baseCalculo><valor>49.85</valor></item><item><tipo>PIS</tipo><aliquota>0.0165</aliquota><baseCalculo>199.4</baseCalculo><valor>3.29</valor></item><item><tipo>COFINS</tipo><aliquota>0.076</aliquota><baseCalculo>199.4</baseCalculo><valor>15.15</valor></item></impostos><subtotalImpostos>68.29</subtotalImpostos><total>267.69</total></item><item><categoria>fibra</categoria><descricao>Internet Fibra 300 Mbps</descricao><quantidade>1</quantidade><unidade>servico</unidade><valorBase>106.38</valorBase><impostos><item><tipo>ICMS</tipo><aliquota>0.25</aliquota><baseCalculo>106.38</baseCalculo><valor>26.59</valor></item><item><tipo>PIS</tipo><aliquota>0.0165</aliquota><baseCalculo>106.38</baseCalculo><valor>1.76</valor></item><item><tipo>COFINS</tipo><aliquota>0.076</aliquota><baseCalculo>106.38</baseCalculo><valor>8.08</valor></item></impostos><subtotalImpostos>36.43</subtotalImpostos><total>142.81</total></item><item><categoria>fibra</categoria><descricao>Internet Fibra 300 Mbps</descricao><quantidade>1</quantidade><unidade>servico</unidade><valorBase>190.82</valorBase><impostos><item><tipo>ICMS</tipo><aliquota>0.25</aliquota><baseCalculo>190.82</baseCalculo><valor>47.7</valor></item><item><tipo>PIS</tipo><aliquota>0.0165</aliquota><baseCalculo>190.82</baseCalculo><valor>3.15</valor></item><item><tipo>COFINS</tipo><aliquota>0.076</aliquota><baseCalculo>190.82</baseCalculo><valor>14.5</valor></item></impostos><subtotalImpostos>65.35</subtotalImpostos><total>256.17</total></item><item><categoria>voz</categoria><descricao>Voz Ilimitada</descricao><quantidade>1</quantidade><unidade>linha</unidade><valorBase>119.65</valorBase><impostos><item><tipo>ICMS</tipo><aliquota>0.25</aliquota><baseCalculo>119.65</baseCalculo><valor>29.91</valor></item><item><tipo>PIS</tipo><aliquota>0.0165</aliquota><baseCalculo>119.65</baseCalculo><valor>1.97</valor></item><item><tipo>COFINS</tipo><aliquota>0.076</aliquota><baseCalculo>119.65</baseCalculo><valor>9.09</valor></item></impostos><subtotalImpostos>40.97</subtotalImpostos><total>160.62</total></item></itens><totais><valorServicosSemImpostos>749.53</valorServicosSemImpostos><impostos><ICMS>187.37</ICMS><PIS>12.37</PIS><COFINS>56.95</COFINS></impostos><totalImpostos>256.69</totalImpostos><totalGeral>1006.22</totalGeral></totais><pagamento><metodo>debito_automatico</metodo><status>em_aberto</status></pagamento><auditoria><criadoEm>2026-01-01T23:22:07.966074Z</criadoEm><atualizadoEm>2026-01-01T23:22:07.966074Z</atualizadoEm><fonte>mock_generator</fonte></auditoria></invoice>