<invoice><tipo>fatura_telecom</tipo><operadora><nome>Vivo</nome><cnpj>00.000.000/0001-01</cnpj></operadora><cliente><razaoSocial>Empresa Beta SA</razaoSocial><cnpj>10000440/0001-90</cnpj></cliente><contrato><numero>46261319</numero></contrato><periodoReferencia><inicio>2026-01-01T23:22:08.035088Z</inicio><fim>2026-01-31T23:22:08.035088Z</fim></periodoReferencia><datas><emissao>2026-02-01T23:22:08.035088Z</emissao><vencimento>2026-02-01T00:00:00Z</vencimento></datas><moeda>BRL</moeda><itens><item><categoria>voz</categoria><descricao>Voz Ilimitada</descricao><quantidade>1</quantidade><unidade>linha</unidade><valorBase>183.68</valorBase><impostos><item><tipo>ICMS</tipo><aliquota>0.25</aliquota><baseCalculo>183.68</baseCalculo><valor>45.92</valor></item><item><tipo>PIS</tipo><aliquota>0.0165</aliquota><baseCalculo>183.68</baseCalculo><valor>3.03</valor></item><item><tipo>COFINS</tipo><aliquota>0.076</aliquota><baseCalculo>183.68</baseCalculo><valor>13.96</valor></item></impostos><subtotalImpostos>62.91</subtotalImpostos><total>246.59</total></item><item><categoria>celular</categoria><descricao>Plano Pós-Pago 20GB</descricao><quantidade>1</quantidade><unidade>linha</unidade><valorBase>162.37</valorBase><impostos><item><tipo>ICMS</tipo><aliquota>0.25</aliquota><baseCalculo>162.37</baseCalculo><valor>40.59</valor></item><item><tipo>PIS</tipo><aliquota>0.0165</aliquota><baseCalculo>162.37</baseCalculo><valor>2.68</valor></item><item><tipo>COFINS</tipo><aliquota>0.076</aliquota><baseCalculo>162.37</baseCalculo><valor>12.34</valor></item></impostos><subtotalImpostos>55.61</subtotalImpostos><total>217.98</total></item><item><categoria>fibra</categoria><descricao>Internet Fibra 300 Mbps</descricao><quantidade>1</quantidade><unidade>servico</unidade><valorBase>96.49</valorBase><impostos><item><tipo>ICMS</tipo><aliquota>0.25</aliquota><baseCalculo>96.49</baseCalculo><valor>24.12</valor></item><item><tipo>PIS</tipo><aliquota>0.0165</aliquota><baseCalculo>96.49</baseCalculo><valor>1.59</valor></item><item><tipo>COFINS</tipo><aliquota>0.076</aliquota><baseCalculo>96.49</baseCalculo><valor>7.33</valor></item></impostos><subtotalImpostos>33.04</subtotalImpostos><total>129.53</total></item><item><categoria>celular</categoria><descricao>Plano Pós-Pago 20GB</descricao><quantidade>1</quantidade><unidade>linha</unidade><valorBase>183.28</valorBase><impostos><item><tipo>ICMS</tipo><aliquota>0.25</aliquota><baseCalculo>183.28</baseCalculo><valor>45.82</valor></item><item><tipo>PIS</tipo><aliquota>0.0165</aliquota><baseCalculo>183.28</baseCalculo><valor>3.02</valor></item><item><tipo>COFINS</tipo><aliquota>0.076</aliquota><baseCalculo>183.28</baseCalculo><valor>13.93</valor></item></impostos><subtotalImpostos>62.77</subtotalImpostos><total>246.05</total></item></itens><totais><valorServicosSemImpostos>625.82</valorServicosSemImpostos><impostos><ICMS>156.45</ICMS><PIS>10.32</PIS><COFINS>47.56</COFINS></impostos><totalImpostos>214.33</totalImpostos><totalGeral>840.15</totalGeral></totais><pagamento><metodo>debito_automatico</metodo><status>em_aberto</status></pagamento><auditoria><criadoEm>2026-02-01T23:22:08.035088Z</criadoEm><atualizadoEm>2026-02-01T23:22:08.035088Z</atualizadoEm><fonte>mock_generator</fonte></auditoria></invoice>