<invoice><tipo>fatura_telecom</tipo><operadora><nome>Vivo</nome><cnpj>00.000.000/0001-01</cnpj></operadora><cliente><razaoSocial>Empresa Sigma Networks</razaoSocial><cnpj>10000802/0001-92</cnpj></cliente><contrato><numero>49306407</numero></contrato><periodoReferencia><inicio>2026-01-01T23:22:08.105320Z</inicio><fim>2026-01-31T23:22:08.105320Z</fim></periodoReferencia><datas><emissao>2026-02-01T23:22:08.105320Z</emissao><vencimento>2026-02-01T00:00:00Z</vencimento></datas><moeda>BRL</moeda><itens><item><categoria>celular</categoria><descricao>Plano Pós-Pago 20GB</descricao><quantidade>1</quantidade><unidade>linha</unidade><valorBase>60.18</valorBase><impostos><item><tipo>ICMS</tipo><aliquota>0.25</aliquota><baseCalculo>60.18</baseCalculo><valor>15.04</valor></item><item><tipo>PIS</tipo><aliquota>0.0165</aliquota><baseCalculo>60.18</baseCalculo><valor>0.99</valor></item><item><tipo>COFINS</tipo><aliquota>0.076</aliquota><baseCalculo>60.18</baseCalculo><valor>4.57</valor></item></impostos><subtotalImpostos>20.6</subtotalImpostos><total>80.78</total></item><item><categoria>televisao</categoria><descricao>TV HD Empresarial (1 ponto)</descricao><quantidade>1</quantidade><unidade>ponto</unidade><valorBase>118.43</valorBase><impostos><item><tipo>ICMS</tipo><aliquota>0.25</aliquota><baseCalculo>118.43</baseCalculo><valor>29.61</valor></item><item><tipo>PIS</tipo><aliquota>0.0165</aliquota><baseCalculo>118.43</baseCalculo><valor>1.95</valor></item><item><tipo>COFINS</tipo><aliquota>0.076</aliquota><baseCalculo>118.43</baseCalculo><valor>9.0</valor></item></impostos><subtotalImpostos>40.56</subtotalImpostos><total>158.99</total></item><item><categoria>celular</categoria><descricao>Plano Pós-Pago 20GB</descricao><quantidade>1</quantidade><unidade>linha</unidade><valorBase>59.6</valorBase><impostos><item><tipo>ICMS</tipo><aliquota>0.25</aliquota><baseCalculo>59.6</baseCalculo><valor>14.9</valor></item><item><tipo>PIS</tipo><aliquota>0.0165</aliquota><baseCalculo>59.6</baseCalculo><valor>0.98</valor></item><item><tipo>COFINS</tipo><aliquota>0.076</aliquota><baseCalculo>59.6</baseCalculo><valor>4.53</valor></item></impostos><subtotalImpostos>20.41</subtotalImpostos><total>80.01</total></item></itens><totais><valorServicosSemImpostos>238.21</valorServicosSemImpostos><impostos><ICMS>59.55</ICMS><PIS>3.92</PIS><COFINS>18.1</COFINS></impostos><totalImpostos>81.57</totalImpostos><totalGeral>319.78</totalGeral></totais><pagamento><metodo>debito_automatico</metodo><status>em_aberto</status></pagamento><auditoria><criadoEm>2026-02-01T23:22:08.105320Z</criadoEm><atualizadoEm>2026-02-01T23:22:08.105320Z</atualizadoEm><fonte>mock_generator</fonte></auditoria></invoice>