<invoice><tipo>fatura_telecom</tipo><operadora><nome>Vivo</nome><cnpj>00.000.000/0001-01</cnpj></operadora><cliente><razaoSocial>Empresa Sigma Networks</razaoSocial><cnpj>10000983/0001-93</cnpj></cliente><contrato><numero>47287022</numero></contrato><periodoReferencia><inicio>2025-12-01T23:22:08.141809Z</inicio><fim>2025-12-31T23:22:08.141809Z</fim></periodoReferencia><datas><emissao>2026-01-01T23:22:08.141809Z</emissao><vencimento>2026-02-01T00:00:00Z</vencimento></datas><moeda>BRL</moeda><itens><item><categoria>fibra</categoria><descricao>Internet Fibra 300 Mbps</descricao><quantidade>1</quantidade><unidade>servico</unidade><valorBase>197.82</valorBase><impostos><item><tipo>ICMS</tipo><aliquota>0.25</aliquota><baseCalculo>197.82</baseCalculo><valor>49.45</valor></item><item><tipo>PIS</tipo><aliquota>0.0165</aliquota><baseCalculo>197.82</baseCalculo><valor>3.26</valor></item><item><tipo>COFINS</tipo><aliquota>0.076</aliquota><baseCalculo>197.82</baseCalculo><valor>15.03</valor></item></impostos><subtotalImpostos>67.74</subtotalImpostos><total>265.56</total></item><item><categoria>celular</categoria><descricao>Plano Pós-Pago 20GB</descricao><quantidade>1</quantidade><unidade>linha</unidade><valorBase>124.35</valorBase><impostos><item><tipo>ICMS</tipo><aliquota>0.25</aliquota><baseCalculo>124.35</baseCalculo><valor>31.09</valor></item><item><tipo>PIS</tipo><aliquota>0.0165</aliquota><baseCalculo>124.35</baseCalculo><valor>2.05</valor></item><item><tipo>COFINS</tipo><aliquota>0.076</aliquota><baseCalculo>124.35</baseCalculo><valor>9.45</valor></item></impostos><subtotalImpostos>42.59</subtotalImpostos><total>166.94</total></item><item><categoria>televisao</categoria><descricao>TV HD Empresarial (1 ponto)</descricao><quantidade>1</quantidade><unidade>ponto</unidade><valorBase>86.56</valorBase><impostos><item><tipo>ICMS</tipo><aliquota>0.25</aliquota><baseCalculo>86.56</baseCalculo><valor>21.64</valor></item><item><tipo>PIS</tipo><aliquota>0.0165</aliquota><baseCalculo>86.56</baseCalculo><valor>1.43</valor></item><item><tipo>COFINS</tipo><aliquota>0.076</aliquota><baseCalculo>86.56</baseCalculo><valor>6.58</valor></item></impostos><subtotalImpostos>29.65</subtotalImpostos><total>116.21</total></item></itens><totais><valorServicosSemImpostos>408.73</valorServicosSemImpostos><impostos><ICMS>102.18</ICMS><PIS>6.74</PIS><COFINS>31.06</COFINS></impostos><totalImpostos>139.98</totalImpostos><totalGeral>548.71</totalGeral></totais><pagamento><metodo>debito_automatico</metodo><status>em_aberto</status></pagamento><auditoria><criadoEm>2026-01-01T23:22:08.141809Z</criadoEm><atualizadoEm>2026-01-01T23:22:08.141809Z</atualizadoEm><fonte>mock_generator</fonte></auditoria></invoice>