<invoice><tipo>fatura_telecom</tipo><operadora><nome>Vivo</nome><cnpj>00.000.000/0001-01</cnpj></operadora><cliente><razaoSocial>Empresa Aurora Digital</razaoSocial><cnpj>10000164/0001-84</cnpj></cliente><contrato><numero>49219151</numero></contrato><periodoReferencia><inicio>2025-12-01T23:22:07.973162Z</inicio><fim>2025-12-31T23:22:07.973162Z</fim></periodoReferencia><datas><emissao>2026-01-01T23:22:07.973162Z</emissao><vencimento>2026-02-01T00:00:00Z</vencimento></datas><moeda>BRL</moeda><itens><item><categoria>fibra</categoria><descricao>Internet Fibra 300 Mbps</descricao><quantidade>1</quantidade><unidade>servico</unidade><valorBase>149.65</valorBase><impostos><item><tipo>ICMS</tipo><aliquota>0.25</aliquota><baseCalculo>149.65</baseCalculo><valor>37.41</valor></item><item><tipo>PIS</tipo><aliquota>0.0165</aliquota><baseCalculo>149.65</baseCalculo><valor>2.47</valor></item><item><tipo>COFINS</tipo><aliquota>0.076</aliquota><baseCalculo>149.65</baseCalculo><valor>11.37</valor></item></impostos><subtotalImpostos>51.25</subtotalImpostos><total>200.9</total></item><item><categoria>fibra</categoria><descricao>Internet Fibra 300 Mbps</descricao><quantidade>1</quantidade><unidade>servico</unidade><valorBase>127.64</valorBase><impostos><item><tipo>ICMS</tipo><aliquota>0.25</aliquota><baseCalculo>127.64</baseCalculo><valor>31.91</valor></item><item><tipo>PIS</tipo><aliquota>0.0165</aliquota><baseCalculo>127.64</baseCalculo><valor>2.11</valor></item><item><tipo>COFINS</tipo><aliquota>0.076</aliquota><baseCalculo>127.64</baseCalculo><valor>9.7</valor></item></impostos><subtotalImpostos>43.72</subtotalImpostos><total>171.36</total></item><item><categoria>voz</categoria><descricao>Voz Ilimitada</descricao><quantidade>1</quantidade><unidade>linha</unidade><valorBase>54.66</valorBase><impostos><item><tipo>ICMS</tipo><aliquota>0.25</aliquota><baseCalculo>54.66</baseCalculo><valor>13.66</valor></item><item><tipo>PIS</tipo><aliquota>0.0165</aliquota><baseCalculo>54.66</baseCalculo><valor>0.9</valor></item><item><tipo>COFINS</tipo><aliquota>0.076</aliquota><baseCalculo>54.66</baseCalculo><valor>4.15</valor></item></impostos><subtotalImpostos>18.71</subtotalImpostos><total>73.37</total></item></itens><totais><valorServicosSemImpostos>331.95</valorServicosSemImpostos><impostos><ICMS>82.98</ICMS><PIS>5.48</PIS><COFINS>25.22</COFINS></impostos><totalImpostos>113.68</totalImpostos><totalGeral>445.63</totalGeral></totais><pagamento><metodo>debito_automatico</metodo><status>em_aberto</status></pagamento><auditoria><criadoEm>2026-01-01T23:22:07.973162Z</criadoEm><atualizadoEm>2026-01-01T23:22:07.973162Z</atualizadoEm><fonte>mock_generator</fonte></auditoria></invoice>