<invoice><tipo>fatura_telecom</tipo><operadora><nome>Vivo</nome><cnpj>00.000.000/0001-01</cnpj></operadora><cliente><razaoSocial>Empresa Nova Telecom</razaoSocial><cnpj>10000111/0001-31</cnpj></cliente><contrato><numero>44437629</numero></contrato><periodoReferencia><inicio>2026-01-01T23:22:07.962448Z</inicio><fim>2026-01-31T23:22:07.962448Z</fim></periodoReferencia><datas><emissao>2026-02-01T23:22:07.962448Z</emissao><vencimento>2026-02-01T00:00:00Z</vencimento></datas><moeda>BRL</moeda><itens><item><categoria>voz</categoria><descricao>Voz Ilimitada</descricao><quantidade>1</quantidade><unidade>linha</unidade><valorBase>178.81</valorBase><impostos><item><tipo>ICMS</tipo><aliquota>0.25</aliquota><baseCalculo>178.81</baseCalculo><valor>44.7</valor></item><item><tipo>PIS</tipo><aliquota>0.0165</aliquota><baseCalculo>178.81</baseCalculo><valor>2.95</valor></item><item><tipo>COFINS</tipo><aliquota>0.076</aliquota><baseCalculo>178.81</baseCalculo><valor>13.59</valor></item></impostos><subtotalImpostos>61.24</subtotalImpostos><total>240.05</total></item><item><categoria>televisao</categoria><descricao>TV HD Empresarial (1 ponto)</descricao><quantidade>1</quantidade><unidade>ponto</unidade><valorBase>75.3</valorBase><impostos><item><tipo>ICMS</tipo><aliquota>0.25</aliquota><baseCalculo>75.3</baseCalculo><valor>18.82</valor></item><item><tipo>PIS</tipo><aliquota>0.0165</aliquota><baseCalculo>75.3</baseCalculo><valor>1.24</valor></item><item><tipo>COFINS</tipo><aliquota>0.076</aliquota><baseCalculo>75.3</baseCalculo><valor>5.72</valor></item></impostos><subtotalImpostos>25.78</subtotalImpostos><total>101.08</total></item><item><categoria>fibra</categoria><descricao>Internet Fibra 300 Mbps</descricao><quantidade>1</quantidade><unidade>servico</unidade><valorBase>199.88</valorBase><impostos><item><tipo>ICMS</tipo><aliquota>0.25</aliquota><baseCalculo>199.88</baseCalculo><valor>49.97</valor></item><item><tipo>PIS</tipo><aliquota>0.0165</aliquota><baseCalculo>199.88</baseCalculo><valor>3.3</valor></item><item><tipo>COFINS</tipo><aliquota>0.076</aliquota><baseCalculo>199.88</baseCalculo><valor>15.19</valor></item></impostos><subtotalImpostos>68.46</subtotalImpostos><total>268.34</total></item><item><categoria>celular</categoria><descricao>Plano Pós-Pago 20GB</descricao><quantidade>1</quantidade><unidade>linha</unidade><valorBase>182.19</valorBase><impostos><item><tipo>ICMS</tipo><aliquota>0.25</aliquota><baseCalculo>182.19</baseCalculo><valor>45.55</valor></item><item><tipo>PIS</tipo><aliquota>0.0165</aliquota><baseCalculo>182.19</baseCalculo><valor>3.01</valor></item><item><tipo>COFINS</tipo><aliquota>0.076</aliquota><baseCalculo>182.19</baseCalculo><valor>13.85</valor></item></impostos><subtotalImpostos>62.41</subtotalImpostos><total>244.6</total></item><item><categoria>televisao</categoria><descricao>TV HD Empresarial (1 ponto)</descricao><quantidade>1</quantidade><unidade>ponto</unidade><valorBase>52.52</valorBase><impostos><item><tipo>ICMS</tipo><aliquota>0.25</aliquota><baseCalculo>52.52</baseCalculo><valor>13.13</valor></item><item><tipo>PIS</tipo><aliquota>0.0165</aliquota><baseCalculo>52.52</baseCalculo><valor>0.87</valor></item><item><tipo>COFINS</tipo><aliquota>0.076</aliquota><baseCalculo>52.52</baseCalculo><valor>3.99</valor></item></impostos><subtotalImpostos>17.99</subtotalImpostos><total>70.51</total></item></itens><totais><valorServicosSemImpostos>688.7</valorServicosSemImpostos><impostos><ICMS>172.17</ICMS><PIS>11.37</PIS><COFINS>52.34</COFINS></impostos><totalImpostos>235.88</totalImpostos><totalGeral>924.58</totalGeral></totais><pagamento><metodo>debito_automatico</metodo><status>em_aberto</status></pagamento><auditoria><criadoEm>2026-02-01T23:22:07.962448Z</criadoEm><atualizadoEm>2026-02-01T23:22:07.962448Z</atualizadoEm><fonte>mock_generator</fonte></auditoria></invoice>